igwrapper/__init__.py
igwrapper/clients/__init__.py
igwrapper/clients/aiorest.py
igwrapper/clients/aiowrapper.py
igwrapper/clients/exceptions.py
igwrapper/models/__init__.py
igwrapper/models/accounts.py
igwrapper/models/activities.py
igwrapper/models/auth.py
igwrapper/models/enums.py
igwrapper/models/models.py
igwrapper/models/position.py
igwrapper/models/prices.py
igwrapper/models/transactions.py
igwrapper-0.1.9.dist-info/WHEEL
igwrapper-0.1.9.dist-info/METADATA
igwrapper-0.1.9.dist-info/RECORD
